json_scout-0.1.2.dist-info/licenses/LICENSE
jsonscout/__init__.py
json_scout-0.1.2.dist-info/METADATA
json_scout-0.1.2.dist-info/WHEEL
json_scout-0.1.2.dist-info/top_level.txt
json_scout-0.1.2.dist-info/RECORD
