Metadata-Version: 2.4
Name: json-scout
Version: 0.1.2
Summary: ⚠️ DEPRECATED: This package has been renamed to 'json-anatomy'. Please use 'json-anatomy' instead.
Author-email: Chathura Jayalath <chathura@example.com>
Maintainer-email: Chathura Jayalath <chathura@example.com>
License: Apache-2.0
Project-URL: Homepage, https://github.com/deamonpog/json-anatomy
Project-URL: Documentation, https://deamonpog.github.io/json-anatomy/
Project-URL: Repository, https://github.com/deamonpog/json-anatomy
Project-URL: Migration Guide, https://github.com/deamonpog/json-anatomy/blob/main/MIGRATION.md
Project-URL: New Package (json-anatomy), https://pypi.org/project/json-anatomy/
Keywords: json,deprecated,json-anatomy
Classifier: Development Status :: 7 - Inactive
Classifier: Intended Audience :: Developers
Classifier: License :: OSI Approved :: Apache Software License
Classifier: Operating System :: OS Independent
Classifier: Programming Language :: Python :: 3
Classifier: Programming Language :: Python :: 3.7
Classifier: Programming Language :: Python :: 3.8
Classifier: Programming Language :: Python :: 3.9
Classifier: Programming Language :: Python :: 3.10
Classifier: Programming Language :: Python :: 3.11
Classifier: Programming Language :: Python :: 3.12
Classifier: Topic :: Software Development :: Libraries :: Python Modules
Requires-Python: >=3.7
License-File: LICENSE
Dynamic: license-file
